[{"id":"1","name":"Airpods Wireless Bluetooth Headphones","description":"Bluetooth technology lets you connect it with compatible devices wirelessly High-quality AAC audio offers immersive listening experience Built-in microphone allows you to take calls while working","price":89.99},{"id":"2","name":"iPhone 11 Pro 256GB Memory","description":"Introducing the iPhone 11 Pro. A transformative triple-camera system that adds tons of capability without complexity. An unprecedented leap in battery life","price":599.99}]